Metadata-Version: 2.0
Name: odoo10-addon-web-responsive
Version: 10.0.1.2.3
Summary: It provides a mobile compliant interface for Odoo Community web
Home-page: https://laslabs.com/
Author: LasLabs, Tecnativa, Odoo Community Association (OCA)
Author-email: support@odoo-community.org
License: LGPL-3
Platform: UNKNOWN
Classifier: Programming Language :: Python
Classifier: Framework :: Odoo
Classifier: License :: OSI Approved :: GNU Lesser General Public License v3 (LGPLv3)
Requires-Python: ~=2.7
Requires-Dist: odoo (<10.1dev,>=10.0)
